purreal/__init__.py
purreal/pooler.py
purreal/shutdown.py
purreal-0.1.2.dist-info/METADATA
purreal-0.1.2.dist-info/WHEEL
purreal-0.1.2.dist-info/licenses/LICENSE
purreal-0.1.2.dist-info/RECORD
