Metadata-Version: 2.4
Name: purreal
Version: 0.1.2
Summary: Production-grade async connection pooler for SurrealDB
Project-URL: Homepage, https://github.com/dyleeeeeeee/purreal
Project-URL: Issues, https://github.com/dyleeeeeeee/purreal/issues
Author-email: Dylee <calistaff33@proton.me>
License-Expression: GPL-3.0
License-File: LICENSE
Keywords: async,concurrency,connection-pool,database,pooling,surrealdb
Classifier: Development Status :: 4 - Beta
Classifier: Framework :: AsyncIO
Classifier: Intended Audience :: Developers
Classifier: License :: OSI Approved :: GNU General Public License v3 (GPLv3)
Classifier: Operating System :: OS Independent
Classifier: Programming Language :: Python :: 3
Classifier: Programming Language :: Python :: 3.11
Classifier: Programming Language :: Python :: 3.12
Classifier: Topic :: Database
Classifier: Topic :: Software Development :: Libraries :: Python Modules
Requires-Python: >=3.11
Requires-Dist: asyncio
Requires-Dist: surrealdb>=0.3.0
Provides-Extra: dev
Requires-Dist: black>=24.0.0; extra == 'dev'
Requires-Dist: mypy>=1.8.0; extra == 'dev'
Requires-Dist: pytest-asyncio>=0.23.0; extra == 'dev'
Requires-Dist: pytest-cov>=4.1.0; extra == 'dev'
Requires-Dist: pytest-mock>=3.12.0; extra == 'dev'
Requires-Dist: pytest-timeout>=2.2.0; extra == 'dev'
Requires-Dist: pytest>=8.0.0; extra == 'dev'
Requires-Dist: ruff>=0.1.0; extra == 'dev'
Provides-Extra: test
Requires-Dist: pytest-asyncio>=0.23.0; extra == 'test'
Requires-Dist: pytest-cov>=4.1.0; extra == 'test'
Requires-Dist: pytest-mock>=3.12.0; extra == 'test'
Requires-Dist: pytest-timeout>=2.2.0; extra == 'test'
Requires-Dist: pytest>=8.0.0; extra == 'test'
